{"v":"4.8.0","meta":{"g":"LottieFiles AE 3.3.6","a":"","k":"","d":"","tc":""},"fr":29.9700012207031,"ip":0,"op":2363.00009624696,"w":200,"h":132,"nm":"camera and crash","ddd":0,"assets":[],"layers":[{"ddd":0,"ind":1,"ty":4,"nm":"Artwork 108 Outlines","sr":1,"ks":{"o":{"a":0,"k":100,"ix":11},"r":{"a":0,"k":0,"ix":10},"p":{"a":0,"k":[100.208,121.676,0],"ix":2},"a":{"a":0,"k":[49.5,56.228,0],"ix":1},"s":{"a":1,"k":[{"i":{"x":[0,0,0.833],"y":[1.01,1.01,-15.75]},"o":{"x":[0.333,0.333,0.333],"y":[0,0,0]},"t":0,"s":[0,0,100]},{"t":20.0000008146167,"s":[200,200,100]}],"ix":6}},"ao":0,"shapes":[{"ty":"gr","it":[{"ind":0,"ty":"sh","ix":1,"ks":{"a":0,"k":{"i":[[1.171,-0.005],[0.727,0.486],[0.335,0.808],[-0.171,0.858],[-0.618,0.618],[-0.858,0.171],[-0.808,-0.335],[-0.485,-0.727],[0,-0.875],[0.828,-0.828]],"o":[[-0.874,0],[-0.727,-0.486],[-0.334,-0.807],[0.17,-0.857],[0.619,-0.618],[0.857,-0.17],[0.807,0.334],[0.486,0.727],[-0.005,1.17],[-0.828,0.828]],"v":[[0.021,5.326],[-2.435,4.581],[-4.063,2.597],[-4.314,0.043],[-3.105,-2.22],[-0.841,-3.43],[1.713,-3.178],[3.696,-1.55],[4.441,0.906],[3.141,4.026]],"c":true},"ix":2},"nm":"Path 1","mn":"ADBE Vector Shape - Group","hd":false},{"ind":1,"ty":"sh","ix":2,"ks":{"a":0,"k":{"i":[[0,0],[0.033,-0.08],[0.061,-0.062],[0.08,-0.033],[0.087,0],[0,0],[0.08,0.033],[0.061,0.061],[0.033,0.08],[-0.001,0.087],[0,0],[-0.033,0.08],[-0.061,0.061],[-0.08,0.033],[-0.086,-0.001],[0,0],[-0.081,-0.033],[-0.062,-0.061],[-0.033,-0.08],[0,-0.087]],"o":[[0.001,0.087],[-0.033,0.08],[-0.061,0.061],[-0.08,0.033],[0,0],[-0.086,0],[-0.08,-0.033],[-0.061,-0.062],[-0.033,-0.08],[0,0],[-0.001,-0.087],[0.033,-0.08],[0.061,-0.061],[0.08,-0.033],[0,0],[0.087,-0.001],[0.08,0.033],[0.061,0.061],[0.033,0.08],[0,0]],"v":[[-6.448,-1.391],[-6.497,-1.138],[-6.64,-0.924],[-6.854,-0.781],[-7.107,-0.732],[-8.043,-0.732],[-8.295,-0.781],[-8.509,-0.924],[-8.652,-1.138],[-8.701,-1.391],[-8.701,-2.324],[-8.652,-2.577],[-8.509,-2.791],[-8.295,-2.934],[-8.043,-2.983],[-7.109,-2.983],[-6.856,-2.934],[-6.642,-2.791],[-6.5,-2.577],[-6.45,-2.324]],"c":true},"ix":2},"nm":"Path 2","mn":"ADBE Vector Shape - Group","hd":false},{"ind":2,"ty":"sh","ix":3,"ks":{"a":0,"k":{"i":[[0.377,0.037],[0,0],[0,0],[0.175,0.107],[0.205,-0.005],[0,0],[0.174,-0.108],[0.089,-0.185],[0,0],[0,0],[0.251,-0.285],[-0.001,-0.38],[0,0],[-0.077,-0.188],[-0.143,-0.144],[-0.187,-0.077],[-0.203,0.001],[0,0],[-1.315,-0.005],[-1.108,0.71],[0,0],[-0.188,0.077],[-0.143,0.143],[-0.078,0.188],[0.002,0.203],[0,0],[0.246,0.287]],"o":[[0,0],[0,0],[-0.09,-0.185],[-0.176,-0.107],[0,0],[-0.205,-0.005],[-0.175,0.107],[0,0],[0,0],[-0.377,0.046],[-0.251,0.284],[0,0],[-0.001,0.203],[0.077,0.188],[0.144,0.143],[0.188,0.077],[0,0],[1.11,0.707],[1.317,-0.001],[0,0],[0.203,0.001],[0.187,-0.077],[0.144,-0.144],[0.077,-0.188],[0,0],[0.023,-0.378],[-0.246,-0.288]],"v":[[9.367,-4.778],[4.694,-5.36],[3.711,-7.383],[3.306,-7.83],[2.723,-7.987],[-2.658,-7.987],[-3.239,-7.83],[-3.642,-7.383],[-4.625,-5.36],[-9.325,-4.778],[-10.299,-4.265],[-10.688,-3.235],[-10.688,5.353],[-10.573,5.945],[-10.239,6.447],[-9.737,6.781],[-9.145,6.896],[-3.714,6.896],[-0.002,7.985],[3.711,6.896],[9.142,6.896],[9.734,6.781],[10.235,6.447],[10.57,5.945],[10.684,5.353],[10.684,-3.235],[10.337,-4.272]],"c":true},"ix":2},"nm":"Path 3","mn":"ADBE Vector Shape - Group","hd":false},{"ty":"mm","mm":1,"nm":"Merge Paths 1","mn":"ADBE Vector Filter - Merge","hd":false},{"ty":"fl","c":{"a":0,"k":[1,1,1,1],"ix":4},"o":{"a":0,"k":100,"ix":5},"r":1,"bm":0,"nm":"Fill 1","mn":"ADBE Vector Graphic - Fill","hd":false},{"ty":"tr","p":{"a":0,"k":[25.688,21.986],"ix":2},"a":{"a":0,"k":[0,0],"ix":1},"s":{"a":0,"k":[100,100],"ix":3},"r":{"a":0,"k":0,"ix":6},"o":{"a":0,"k":100,"ix":7},"sk":{"a":0,"k":0,"ix":4},"sa":{"a":0,"k":0,"ix":5},"nm":"Transform"}],"nm":"Group 1","np":7,"cix":2,"bm":0,"ix":1,"mn":"ADBE Vector Group","hd":false},{"ty":"gr","it":[{"ind":0,"ty":"sh","ix":1,"ks":{"a":0,"k":{"i":[[0,0],[0.348,-0.133],[-0.088,-0.167],[0.001,-0.19],[0.148,-0.199],[0.237,-0.074],[0.234,0.08],[0.142,0.203],[0.001,-0.372],[-0.321,-0.485],[-0.537,-0.225],[-0.571,0.113],[-0.412,0.411],[-0.112,0.571],[0.224,0.537],[0.486,0.32],[0.581,-0.004]],"o":[[-0.372,0.001],[0.157,0.106],[0.089,0.168],[-0.002,0.248],[-0.148,0.199],[-0.236,0.073],[-0.235,-0.081],[-0.133,0.348],[-0.004,0.582],[0.32,0.486],[0.536,0.225],[0.571,-0.112],[0.411,-0.412],[0.112,-0.571],[-0.225,-0.537],[-0.485,-0.32],[0,0]],"v":[[-0.046,-2.961],[-1.135,-2.758],[-0.764,-2.341],[-0.631,-1.797],[-0.861,-1.11],[-1.452,-0.69],[-2.176,-0.701],[-2.756,-1.138],[-2.958,-0.049],[-2.473,1.588],[-1.158,2.678],[0.54,2.85],[2.048,2.047],[2.85,0.54],[2.678,-1.159],[1.589,-2.474],[-0.049,-2.959]],"c":true},"ix":2},"nm":"Path 1","mn":"ADBE Vector Shape - Group","hd":false},{"ty":"fl","c":{"a":0,"k":[1,1,1,1],"ix":4},"o":{"a":0,"k":100,"ix":5},"r":1,"bm":0,"nm":"Fill 1","mn":"ADBE Vector Graphic - Fill","hd":false},{"ty":"tr","p":{"a":0,"k":[25.755,22.924],"ix":2},"a":{"a":0,"k":[0,0],"ix":1},"s":{"a":0,"k":[100,100],"ix":3},"r":{"a":0,"k":0,"ix":6},"o":{"a":0,"k":100,"ix":7},"sk":{"a":0,"k":0,"ix":4},"sa":{"a":0,"k":0,"ix":5},"nm":"Transform"}],"nm":"Group 2","np":2,"cix":2,"bm":0,"ix":2,"mn":"ADBE Vector Group","hd":false},{"ty":"gr","it":[{"ind":0,"ty":"sh","ix":1,"ks":{"a":0,"k":{"i":[[0,0],[1.22,-0.094],[0,0],[-0.45,-0.137],[-0.415,0.222],[-0.138,0.45],[0.221,0.415]],"o":[[-1.08,0.573],[0,0],[0.222,0.415],[0.45,0.137],[0.415,-0.221],[0.137,-0.45],[0,0]],"v":[[0.309,-3.728],[-3.178,-2.717],[-0.222,2.791],[0.827,3.654],[2.178,3.522],[3.041,2.474],[2.909,1.123]],"c":true},"ix":2},"nm":"Path 1","mn":"ADBE Vector Shape - Group","hd":false},{"ty":"fl","c":{"a":0,"k":[1,1,1,1],"ix":4},"o":{"a":0,"k":100,"ix":5},"r":1,"bm":0,"nm":"Fill 1","mn":"ADBE Vector Graphic - Fill","hd":false},{"ty":"tr","p":{"a":0,"k":[29.468,34.273],"ix":2},"a":{"a":0,"k":[0,0],"ix":1},"s":{"a":0,"k":[100,100],"ix":3},"r":{"a":0,"k":0,"ix":6},"o":{"a":0,"k":100,"ix":7},"sk":{"a":0,"k":0,"ix":4},"sa":{"a":0,"k":0,"ix":5},"nm":"Transform"}],"nm":"Group 3","np":4,"cix":2,"bm":0,"ix":3,"mn":"ADBE Vector Group","hd":false},{"ty":"gr","it":[{"ind":0,"ty":"sh","ix":1,"ks":{"a":0,"k":{"i":[[0,0],[-0.136,-0.449],[-0.412,-0.224],[-0.29,-0.004],[-0.275,0.164],[-0.155,0.279],[0,0],[1.076,0.583]],"o":[[-0.217,0.416],[0.137,0.448],[0.26,0.13],[0.32,-0.004],[0.275,-0.164],[0,0],[-1.222,-0.084],[0,0]],"v":[[-2.913,1.124],[-3.038,2.473],[-2.182,3.523],[-1.348,3.727],[-0.439,3.471],[0.217,2.794],[3.174,-2.715],[-0.312,-3.727]],"c":true},"ix":2},"nm":"Path 1","mn":"ADBE Vector Shape - Group","hd":false},{"ty":"fl","c":{"a":0,"k":[1,1,1,1],"ix":4},"o":{"a":0,"k":100,"ix":5},"r":1,"bm":0,"nm":"Fill 1","mn":"ADBE Vector Graphic - Fill","hd":false},{"ty":"tr","p":{"a":0,"k":[21.954,34.271],"ix":2},"a":{"a":0,"k":[0,0],"ix":1},"s":{"a":0,"k":[100,100],"ix":3},"r":{"a":0,"k":0,"ix":6},"o":{"a":0,"k":100,"ix":7},"sk":{"a":0,"k":0,"ix":4},"sa":{"a":0,"k":0,"ix":5},"nm":"Transform"}],"nm":"Group 4","np":2,"cix":2,"bm":0,"ix":4,"mn":"ADBE Vector Group","hd":false},{"ty":"gr","it":[{"ind":0,"ty":"sh","ix":1,"ks":{"a":0,"k":{"i":[[1.171,-0.005],[0.727,0.486],[0.335,0.808],[-0.171,0.858],[-0.618,0.618],[-0.858,0.171],[-0.808,-0.335],[-0.485,-0.727],[0,-0.875],[0.828,-0.828]],"o":[[-0.874,0],[-0.727,-0.486],[-0.334,-0.807],[0.17,-0.857],[0.619,-0.618],[0.857,-0.17],[0.807,0.334],[0.486,0.727],[-0.005,1.17],[-0.828,0.828]],"v":[[0.021,5.326],[-2.435,4.581],[-4.063,2.597],[-4.314,0.043],[-3.105,-2.22],[-0.841,-3.43],[1.713,-3.178],[3.696,-1.55],[4.441,0.906],[3.141,4.026]],"c":true},"ix":2},"nm":"Path 1","mn":"ADBE Vector Shape - Group","hd":false},{"ind":1,"ty":"sh","ix":2,"ks":{"a":0,"k":{"i":[[0,0],[0.033,-0.08],[0.061,-0.062],[0.08,-0.033],[0.087,0],[0,0],[0.08,0.033],[0.061,0.061],[0.033,0.08],[-0.001,0.087],[0,0],[-0.033,0.08],[-0.061,0.061],[-0.08,0.033],[-0.086,-0.001],[0,0],[-0.081,-0.033],[-0.062,-0.061],[-0.033,-0.08],[0,-0.087]],"o":[[0.001,0.087],[-0.033,0.08],[-0.061,0.061],[-0.08,0.033],[0,0],[-0.086,0],[-0.08,-0.033],[-0.061,-0.062],[-0.033,-0.08],[0,0],[-0.001,-0.087],[0.033,-0.08],[0.061,-0.061],[0.08,-0.033],[0,0],[0.087,-0.001],[0.08,0.033],[0.061,0.061],[0.033,0.08],[0,0]],"v":[[-6.448,-1.391],[-6.497,-1.138],[-6.64,-0.924],[-6.854,-0.781],[-7.107,-0.732],[-8.043,-0.732],[-8.295,-0.781],[-8.509,-0.924],[-8.652,-1.138],[-8.701,-1.391],[-8.701,-2.324],[-8.652,-2.577],[-8.509,-2.791],[-8.295,-2.934],[-8.043,-2.983],[-7.109,-2.983],[-6.856,-2.934],[-6.642,-2.791],[-6.5,-2.577],[-6.45,-2.324]],"c":true},"ix":2},"nm":"Path 2","mn":"ADBE Vector Shape - Group","hd":false},{"ind":2,"ty":"sh","ix":3,"ks":{"a":0,"k":{"i":[[0.377,0.037],[0,0],[0,0],[0.175,0.107],[0.205,-0.005],[0,0],[0.174,-0.108],[0.089,-0.185],[0,0],[0,0],[0.251,-0.285],[-0.001,-0.38],[0,0],[-0.077,-0.188],[-0.143,-0.144],[-0.187,-0.077],[-0.203,0.001],[0,0],[-1.315,-0.005],[-1.108,0.71],[0,0],[-0.188,0.077],[-0.143,0.143],[-0.078,0.188],[0.002,0.203],[0,0],[0.246,0.287]],"o":[[0,0],[0,0],[-0.09,-0.185],[-0.176,-0.107],[0,0],[-0.205,-0.005],[-0.175,0.107],[0,0],[0,0],[-0.377,0.046],[-0.251,0.284],[0,0],[-0.001,0.203],[0.077,0.188],[0.144,0.143],[0.188,0.077],[0,0],[1.11,0.707],[1.317,-0.001],[0,0],[0.203,0.001],[0.187,-0.077],[0.144,-0.144],[0.077,-0.188],[0,0],[0.023,-0.378],[-0.246,-0.288]],"v":[[9.367,-4.778],[4.694,-5.36],[3.711,-7.383],[3.306,-7.83],[2.723,-7.987],[-2.658,-7.987],[-3.239,-7.83],[-3.642,-7.383],[-4.625,-5.36],[-9.325,-4.778],[-10.299,-4.265],[-10.688,-3.235],[-10.688,5.353],[-10.573,5.945],[-10.239,6.447],[-9.737,6.781],[-9.145,6.896],[-3.714,6.896],[-0.002,7.985],[3.711,6.896],[9.142,6.896],[9.734,6.781],[10.235,6.447],[10.57,5.945],[10.684,5.353],[10.684,-3.235],[10.337,-4.272]],"c":true},"ix":2},"nm":"Path 3","mn":"ADBE Vector Shape - Group","hd":false},{"ty":"mm","mm":1,"nm":"Merge Paths 1","mn":"ADBE Vector Filter - Merge","hd":false},{"ty":"fl","c":{"a":0,"k":[1,1,1,1],"ix":4},"o":{"a":0,"k":100,"ix":5},"r":1,"bm":0,"nm":"Fill 1","mn":"ADBE Vector Graphic - Fill","hd":false},{"ty":"tr","p":{"a":0,"k":[25.688,21.986],"ix":2},"a":{"a":0,"k":[0,0],"ix":1},"s":{"a":0,"k":[100,100],"ix":3},"r":{"a":0,"k":0,"ix":6},"o":{"a":0,"k":100,"ix":7},"sk":{"a":0,"k":0,"ix":4},"sa":{"a":0,"k":0,"ix":5},"nm":"Transform"}],"nm":"Group 5","np":7,"cix":2,"bm":0,"ix":5,"mn":"ADBE Vector Group","hd":false},{"ty":"gr","it":[{"ind":0,"ty":"sh","ix":1,"ks":{"a":0,"k":{"i":[[0,0],[0.348,-0.133],[-0.088,-0.167],[0.001,-0.19],[0.148,-0.199],[0.237,-0.074],[0.234,0.08],[0.142,0.203],[0.001,-0.372],[-0.321,-0.485],[-0.537,-0.225],[-0.571,0.113],[-0.412,0.411],[-0.112,0.571],[0.224,0.537],[0.486,0.32],[0.581,-0.004]],"o":[[-0.372,0.001],[0.157,0.106],[0.089,0.168],[-0.002,0.248],[-0.148,0.199],[-0.236,0.073],[-0.235,-0.081],[-0.133,0.348],[-0.004,0.582],[0.32,0.486],[0.536,0.225],[0.571,-0.112],[0.411,-0.412],[0.112,-0.571],[-0.225,-0.537],[-0.485,-0.32],[0,0]],"v":[[-0.046,-2.961],[-1.135,-2.758],[-0.764,-2.341],[-0.631,-1.797],[-0.861,-1.11],[-1.452,-0.69],[-2.176,-0.701],[-2.756,-1.138],[-2.958,-0.049],[-2.473,1.588],[-1.158,2.678],[0.54,2.85],[2.048,2.047],[2.85,0.54],[2.678,-1.159],[1.589,-2.474],[-0.049,-2.959]],"c":true},"ix":2},"nm":"Path 1","mn":"ADBE Vector Shape - Group","hd":false},{"ty":"fl","c":{"a":0,"k":[1,1,1,1],"ix":4},"o":{"a":0,"k":100,"ix":5},"r":1,"bm":0,"nm":"Fill 1","mn":"ADBE Vector Graphic - Fill","hd":false},{"ty":"tr","p":{"a":0,"k":[25.755,22.924],"ix":2},"a":{"a":0,"k":[0,0],"ix":1},"s":{"a":0,"k":[100,100],"ix":3},"r":{"a":0,"k":0,"ix":6},"o":{"a":0,"k":100,"ix":7},"sk":{"a":0,"k":0,"ix":4},"sa":{"a":0,"k":0,"ix":5},"nm":"Transform"}],"nm":"Group 6","np":2,"cix":2,"bm":0,"ix":6,"mn":"ADBE Vector Group","hd":false},{"ty":"gr","it":[{"ind":0,"ty":"sh","ix":1,"ks":{"a":0,"k":{"i":[[0,0],[1.22,-0.094],[0,0],[-0.45,-0.137],[-0.415,0.222],[-0.138,0.45],[0.221,0.415]],"o":[[-1.08,0.573],[0,0],[0.222,0.415],[0.45,0.137],[0.415,-0.221],[0.137,-0.45],[0,0]],"v":[[0.309,-3.728],[-3.178,-2.717],[-0.222,2.791],[0.827,3.654],[2.178,3.522],[3.041,2.474],[2.909,1.123]],"c":true},"ix":2},"nm":"Path 1","mn":"ADBE Vector Shape - Group","hd":false},{"ty":"fl","c":{"a":0,"k":[1,1,1,1],"ix":4},"o":{"a":0,"k":100,"ix":5},"r":1,"bm":0,"nm":"Fill 1","mn":"ADBE Vector Graphic - Fill","hd":false},{"ty":"tr","p":{"a":0,"k":[29.468,34.273],"ix":2},"a":{"a":0,"k":[0,0],"ix":1},"s":{"a":0,"k":[100,100],"ix":3},"r":{"a":0,"k":0,"ix":6},"o":{"a":0,"k":100,"ix":7},"sk":{"a":0,"k":0,"ix":4},"sa":{"a":0,"k":0,"ix":5},"nm":"Transform"}],"nm":"Group 7","np":4,"cix":2,"bm":0,"ix":7,"mn":"ADBE Vector Group","hd":false},{"ty":"gr","it":[{"ind":0,"ty":"sh","ix":1,"ks":{"a":0,"k":{"i":[[0,0],[-0.136,-0.449],[-0.412,-0.224],[-0.29,-0.004],[-0.275,0.164],[-0.155,0.279],[0,0],[1.076,0.583]],"o":[[-0.217,0.416],[0.137,0.448],[0.26,0.13],[0.32,-0.004],[0.275,-0.164],[0,0],[-1.222,-0.084],[0,0]],"v":[[-2.913,1.124],[-3.038,2.473],[-2.182,3.523],[-1.348,3.727],[-0.439,3.471],[0.217,2.794],[3.174,-2.715],[-0.312,-3.727]],"c":true},"ix":2},"nm":"Path 1","mn":"ADBE Vector Shape - Group","hd":false},{"ty":"fl","c":{"a":0,"k":[1,1,1,1],"ix":4},"o":{"a":0,"k":100,"ix":5},"r":1,"bm":0,"nm":"Fill 1","mn":"ADBE Vector Graphic - Fill","hd":false},{"ty":"tr","p":{"a":0,"k":[21.954,34.271],"ix":2},"a":{"a":0,"k":[0,0],"ix":1},"s":{"a":0,"k":[100,100],"ix":3},"r":{"a":0,"k":0,"ix":6},"o":{"a":0,"k":100,"ix":7},"sk":{"a":0,"k":0,"ix":4},"sa":{"a":0,"k":0,"ix":5},"nm":"Transform"}],"nm":"Group 8","np":2,"cix":2,"bm":0,"ix":8,"mn":"ADBE Vector Group","hd":false},{"ty":"gr","it":[{"ind":0,"ty":"sh","ix":1,"ks":{"a":0,"k":{"i":[[-11.779,0],[0,-11.779],[11.779,0],[0,11.779]],"o":[[11.779,0],[0,11.779],[-11.779,0],[0,-11.779]],"v":[[0,-21.327],[21.327,0],[0,21.327],[-21.327,0]],"c":true},"ix":2},"nm":"Path 1","mn":"ADBE Vector Shape - Group","hd":false},{"ty":"fl","c":{"a":0,"k":[0.286274509804,0.360784313725,0.909803981407,1],"ix":4},"o":{"a":0,"k":100,"ix":5},"r":1,"bm":0,"nm":"Fill 1","mn":"ADBE Vector Graphic - Fill","hd":false},{"ty":"tr","p":{"a":0,"k":[25.897,25.897],"ix":2},"a":{"a":0,"k":[0,0],"ix":1},"s":{"a":0,"k":[100,100],"ix":3},"r":{"a":0,"k":0,"ix":6},"o":{"a":0,"k":100,"ix":7},"sk":{"a":0,"k":0,"ix":4},"sa":{"a":0,"k":0,"ix":5},"nm":"Transform"}],"nm":"Group 9","np":2,"cix":2,"bm":0,"ix":9,"mn":"ADBE Vector Group","hd":false},{"ty":"gr","it":[{"ind":0,"ty":"sh","ix":1,"ks":{"a":0,"k":{"i":[[0,0],[-0.872,-0.23],[-0.208,0.012],[-0.185,0.095],[-0.131,0.162],[-0.054,0.201],[0.031,0.206],[0.112,0.175],[0.174,0.115],[0.205,0.035],[0.22,-0.869]],"o":[[-0.233,0.865],[0.195,0.073],[0.208,-0.013],[0.185,-0.096],[0.13,-0.162],[0.054,-0.201],[-0.032,-0.206],[-0.112,-0.175],[-0.173,-0.115],[-0.862,-0.239],[0,0]],"v":[[8.709,4.451],[10.692,5.754],[11.303,5.846],[11.899,5.683],[12.378,5.292],[12.658,4.742],[12.692,4.125],[12.473,3.547],[12.039,3.107],[11.465,2.88],[8.719,4.461]],"c":true},"ix":2},"nm":"Path 1","mn":"ADBE Vector Shape - Group","hd":false},{"ind":1,"ty":"sh","ix":2,"ks":{"a":0,"k":{"i":[[0,0],[0.09,0.203],[0.254,0.218],[0.323,0.088],[0,0],[0.197,0.005],[0.31,-0.155],[0.224,-0.265],[0,0],[0,0],[0,0]],"o":[[-0.028,-0.22],[-0.136,-0.306],[-0.254,-0.217],[0,0],[-0.191,-0.046],[-0.346,0.021],[-0.309,0.156],[0,0],[0,0],[0,0],[0,0]],"v":[[10.308,-2.201],[10.129,-2.839],[9.536,-3.635],[8.66,-4.099],[2.912,-5.641],[2.328,-5.718],[1.333,-5.451],[0.525,-4.813],[-0.988,-2.798],[7.079,-0.629],[10.611,0.329]],"c":true},"ix":2},"nm":"Path 2","mn":"ADBE Vector Shape - Group","hd":false},{"ind":2,"ty":"sh","ix":3,"ks":{"a":0,"k":{"i":[[0,0],[-0.02,-0.199],[-0.1,-0.174],[-0.163,-0.117],[-0.196,-0.04],[-0.233,0.868],[0.284,0.489],[0.507,0.251],[0.199,-0.021],[0.173,-0.101],[0.117,-0.163],[0.039,-0.197]],"o":[[-0.063,0.19],[0.02,0.199],[0.1,0.173],[0.162,0.117],[0.868,0.233],[0.033,-0.565],[-0.284,-0.489],[-0.19,-0.063],[-0.2,0.021],[-0.173,0.101],[-0.116,0.164],[0,0]],"v":[[-4.861,0.037],[-4.926,0.628],[-4.743,1.193],[-4.344,1.633],[-3.8,1.871],[-1.431,1.731],[-1.815,0.115],[-3.028,-1.019],[-3.619,-1.083],[-4.185,-0.899],[-4.625,-0.498],[-4.861,0.049]],"c":true},"ix":2},"nm":"Path 3","mn":"ADBE Vector Shape - Group","hd":false},{"ind":3,"ty":"sh","ix":4,"ks":{"a":0,"k":{"i":[[0,0],[0.397,-0.373],[0.144,-0.096],[0,0],[0.124,-0.157],[0.28,-0.093],[0.285,0.077],[0,0],[0.156,0.12],[0.098,0.171],[0.025,0.196],[-0.051,0.191],[0,0],[0,0],[0,0],[0.12,-0.156],[0.17,-0.099],[0.195,-0.026],[0.191,0.051],[0,0],[0.196,0.222],[0.04,0.293],[-0.051,0.194],[0,0],[0.052,0.167],[-0.141,0.524],[0,0],[-0.3,0.342],[-0.42,0.174],[-0.298,0.037],[0,0],[0,0],[-0.7,0.365],[-0.774,0.028],[-0.51,-0.137],[0,0],[-0.447,-0.284],[-0.437,-0.636],[-0.095,-0.777],[0,0],[0,0],[-0.231,-0.551],[0.16,-0.595]],"o":[[-0.142,0.526],[-0.13,0.116],[0,0],[-0.051,0.194],[-0.181,0.233],[-0.28,0.094],[0,0],[-0.191,-0.051],[-0.157,-0.121],[-0.099,-0.171],[-0.026,-0.195],[0,0],[0,0],[0,0],[-0.051,0.19],[-0.12,0.156],[-0.171,0.098],[-0.196,0.025],[0,0],[-0.285,-0.076],[-0.196,-0.221],[-0.027,-0.198],[0,0],[-0.075,-0.158],[-0.156,-0.52],[0,0],[0.119,-0.439],[0.301,-0.342],[0.279,-0.109],[0,0],[0,0],[0.473,-0.633],[0.687,-0.359],[0.529,-0.019],[0,0],[0.511,0.14],[0.639,0.434],[0.42,0.661],[0,0],[0,0],[0.468,0.371],[0.215,0.577],[0,0]],"v":[[14.321,6.744],[13.497,8.12],[13.085,8.439],[12.427,10.887],[12.162,11.42],[11.454,11.921],[10.588,11.947],[9.138,11.561],[8.613,11.302],[8.227,10.861],[8.039,10.306],[8.077,9.721],[8.464,8.271],[-3.125,5.176],[-3.515,6.626],[-3.774,7.151],[-4.214,7.537],[-4.769,7.725],[-5.354,7.686],[-6.804,7.299],[-7.542,6.842],[-7.905,6.053],[-7.868,5.46],[-7.211,3.012],[-7.402,2.523],[-7.425,0.926],[-6.844,-1.268],[-6.207,-2.455],[-5.111,-3.239],[-4.242,-3.459],[-3.393,-4.596],[-1.886,-6.611],[-0.104,-8.127],[2.115,-8.715],[3.683,-8.536],[9.432,-6.994],[10.878,-6.355],[12.506,-4.736],[13.288,-2.551],[13.589,-0.051],[13.758,1.357],[14.824,2.763],[14.908,4.564]],"c":true},"ix":2},"nm":"Path 4","mn":"ADBE Vector Shape - Group","hd":false},{"ind":4,"ty":"sh","ix":5,"ks":{"a":0,"k":{"i":[[0,0],[-0.06,-0.535],[0,0],[0.088,-0.006],[0.075,0.045],[0.035,0.08],[-0.017,0.086],[0,0],[0.013,0.058],[0.036,0.048],[0.051,0.03],[0.059,0.006],[0,0],[0.066,0.057],[0.021,0.085],[-0.032,0.081],[-0.073,0.049],[0,0],[-0.033,0.052],[-0.009,0.061],[0.017,0.058],[0.041,0.047],[0,0],[0.007,0.087],[-0.045,0.076],[-0.08,0.035],[-0.086,-0.018],[0,0],[-0.058,0.013],[-0.048,0.035],[-0.03,0.051],[-0.006,0.058],[0,0],[-0.058,0.066],[-0.085,0.021],[-0.082,-0.031],[-0.048,-0.073],[0,0],[-0.052,-0.033],[-0.061,-0.009],[-0.059,0.017],[-0.047,0.04],[0,0],[-0.087,0.007],[-0.075,-0.045],[-0.035,-0.08],[0.017,-0.086],[0,0],[0.115,-0.153],[0,0],[0,0],[0.56,-0.559],[0.206,-0.765]],"o":[[-0.134,0.521],[0,0],[-0.068,0.056],[-0.087,0.007],[-0.075,-0.045],[-0.035,-0.08],[0,0],[0.012,-0.059],[-0.013,-0.058],[-0.035,-0.048],[-0.052,-0.029],[0,0],[-0.088,-0.008],[-0.067,-0.057],[-0.021,-0.085],[0.031,-0.082],[0,0],[0.052,-0.033],[0.034,-0.051],[0.009,-0.061],[-0.017,-0.059],[0,0],[-0.056,-0.067],[-0.007,-0.088],[0.045,-0.075],[0.081,-0.035],[0,0],[0.058,0.012],[0.058,-0.012],[0.048,-0.035],[0.029,-0.052],[0,0],[0.009,-0.087],[0.057,-0.066],[0.085,-0.021],[0.081,0.032],[0,0],[0.033,0.051],[0.051,0.033],[0.061,0.009],[0.059,-0.018],[0,0],[0.067,-0.056],[0.088,-0.006],[0.076,0.046],[0.036,0.081],[0,0],[-0.128,0.143],[0,0],[0,0],[-0.764,0.206],[-0.56,0.56],[0,0]],"v":[[-8.873,0.529],[-8.985,2.126],[-10.635,3.486],[-10.874,3.582],[-11.124,3.523],[-11.294,3.33],[-11.322,3.074],[-10.6,-0.505],[-10.601,-0.682],[-10.674,-0.842],[-10.805,-0.96],[-10.973,-1.013],[-14.626,-1.368],[-14.862,-1.469],[-14.997,-1.687],[-14.981,-1.943],[-14.821,-2.144],[-11.765,-4.172],[-11.636,-4.3],[-11.572,-4.47],[-11.585,-4.651],[-11.673,-4.811],[-14.005,-7.646],[-14.101,-7.884],[-14.042,-8.135],[-13.849,-8.305],[-13.593,-8.332],[-9.997,-7.608],[-9.821,-7.609],[-9.661,-7.681],[-9.543,-7.811],[-9.489,-7.978],[-9.134,-11.616],[-9.032,-11.851],[-8.814,-11.984],[-8.558,-11.968],[-8.359,-11.807],[-6.33,-8.751],[-6.202,-8.622],[-6.032,-8.558],[-5.851,-8.571],[-5.691,-8.659],[-2.878,-10.993],[-2.64,-11.089],[-2.39,-11.03],[-2.22,-10.837],[-2.192,-10.581],[-2.719,-7.947],[-3.09,-7.506],[-4.598,-5.491],[-5.115,-4.82],[-7.136,-3.652],[-8.305,-1.63]],"c":true},"ix":2},"nm":"Path 5","mn":"ADBE Vector Shape - Group","hd":false},{"ty":"mm","mm":1,"nm":"Merge Paths 1","mn":"ADBE Vector Filter - Merge","hd":false},{"ty":"fl","c":{"a":0,"k":[1,1,1,1],"ix":4},"o":{"a":0,"k":100,"ix":5},"r":1,"bm":0,"nm":"Fill 1","mn":"ADBE Vector Graphic - Fill","hd":false},{"ty":"tr","p":{"a":0,"k":[71.441,26.431],"ix":2},"a":{"a":0,"k":[0,0],"ix":1},"s":{"a":0,"k":[100,100],"ix":3},"r":{"a":0,"k":0,"ix":6},"o":{"a":0,"k":100,"ix":7},"sk":{"a":0,"k":0,"ix":4},"sa":{"a":0,"k":0,"ix":5},"nm":"Transform"}],"nm":"Group 10","np":9,"cix":2,"bm":0,"ix":10,"mn":"ADBE Vector Group","hd":false},{"ty":"gr","it":[{"ind":0,"ty":"sh","ix":1,"ks":{"a":0,"k":{"i":[[-11.779,0],[0,-11.779],[11.779,0],[0,11.779]],"o":[[11.779,0],[0,11.779],[-11.779,0],[0,-11.779]],"v":[[0,-21.327],[21.327,0],[0,21.327],[-21.327,0]],"c":true},"ix":2},"nm":"Path 1","mn":"ADBE Vector Shape - Group","hd":false},{"ty":"fl","c":{"a":0,"k":[0.945098099054,0.490196108351,0.160784313725,1],"ix":4},"o":{"a":0,"k":100,"ix":5},"r":1,"bm":0,"nm":"Fill 1","mn":"ADBE Vector Graphic - Fill","hd":false},{"ty":"tr","p":{"a":0,"k":[72.327,26.328],"ix":2},"a":{"a":0,"k":[0,0],"ix":1},"s":{"a":0,"k":[100,100],"ix":3},"r":{"a":0,"k":0,"ix":6},"o":{"a":0,"k":100,"ix":7},"sk":{"a":0,"k":0,"ix":4},"sa":{"a":0,"k":0,"ix":5},"nm":"Transform"}],"nm":"Group 11","np":2,"cix":2,"bm":0,"ix":11,"mn":"ADBE Vector Group","hd":false},{"ty":"gr","it":[{"ind":0,"ty":"sh","ix":1,"ks":{"a":0,"k":{"i":[[0,0],[5.509,-0.89],[1.417,0],[0,14.303],[-14.302,0],[-0.977,-0.111],[-10.385,1.19],[-1.007,0],[0,-14.303],[14.303,0],[1.522,0.278],[4.055,-4.055],[0,0],[0.781,0.781]],"o":[[-3.946,-3.946],[-1.354,0.218],[-14.302,0],[0,-14.303],[1.008,0],[10.386,1.19],[0.978,-0.111],[14.303,0],[0,14.303],[-1.602,0],[-5.642,-1.033],[0,0],[-0.781,0.781],[0,0]],"v":[[-3.78,26.316],[-19.339,22.797],[-23.5,23.129],[-49.397,-2.768],[-23.5,-28.665],[-20.521,-28.496],[20.521,-28.496],[23.5,-28.665],[49.397,-2.768],[23.5,23.129],[18.807,22.705],[2.793,26.099],[0.812,28.08],[-2.016,28.08]],"c":true},"ix":2},"nm":"Path 1","mn":"ADBE Vector Shape - Group","hd":false},{"ty":"fl","c":{"a":0,"k":[1,1,1,1],"ix":4},"o":{"a":0,"k":100,"ix":5},"r":1,"bm":0,"nm":"Fill 1","mn":"ADBE Vector Graphic - Fill","hd":false},{"ty":"tr","p":{"a":0,"k":[49.397,28.665],"ix":2},"a":{"a":0,"k":[0,0],"ix":1},"s":{"a":0,"k":[100,100],"ix":3},"r":{"a":0,"k":0,"ix":6},"o":{"a":0,"k":100,"ix":7},"sk":{"a":0,"k":0,"ix":4},"sa":{"a":0,"k":0,"ix":5},"nm":"Transform"}],"nm":"Group 12","np":4,"cix":2,"bm":0,"ix":12,"mn":"ADBE Vector Group","hd":false}],"ip":0,"op":2363.00009624696,"st":0,"bm":0}],"markers":[]}